<?xml version="1.0" encoding="utf-8" ?>
<dwsync>
<file name="doc.png" server="C:/xampp/htdocs/AtlasSonoroBocetoPreliminar/" local="129344772560000000" remote="129344772560000000" />
<file name="email.png" server="C:/xampp/htdocs/AtlasSonoroBocetoPreliminar/" local="129344772560000000" remote="129344772560000000" />
<file name="external.png" server="C:/xampp/htdocs/AtlasSonoroBocetoPreliminar/" local="129344772560000000" remote="129344772560000000" />
<file name="feed.png" server="C:/xampp/htdocs/AtlasSonoroBocetoPreliminar/" local="129344772560000000" remote="129344772560000000" />
<file name="im.png" server="C:/xampp/htdocs/AtlasSonoroBocetoPreliminar/" local="129344772560000000" remote="129344772560000000" />
<file name="pdf.png" server="C:/xampp/htdocs/AtlasSonoroBocetoPreliminar/" local="129344772560000000" remote="129344772560000000" />
<file name="visited.png" server="C:/xampp/htdocs/AtlasSonoroBocetoPreliminar/" local="129344772560000000" remote="129344772560000000" />
<file name="xls.png" server="C:/xampp/htdocs/AtlasSonoroBocetoPreliminar/" local="129344772560000000" remote="129344772560000000" />
<file name="doc.png" server="atlassonoro.gaiared.com//httpdocs/" local="129344772560000000" remote="129392519400000000" />
<file name="email.png" server="atlassonoro.gaiared.com//httpdocs/" local="129344772560000000" remote="129392519400000000" />
<file name="external.png" server="atlassonoro.gaiared.com//httpdocs/" local="129344772560000000" remote="129392519400000000" />
<file name="feed.png" server="atlassonoro.gaiared.com//httpdocs/" local="129344772560000000" remote="129392519400000000" />
<file name="im.png" server="atlassonoro.gaiared.com//httpdocs/" local="129344772560000000" remote="129392519400000000" />
<file name="pdf.png" server="atlassonoro.gaiared.com//httpdocs/" local="129344772560000000" remote="129392519400000000" />
<file name="visited.png" server="atlassonoro.gaiared.com//httpdocs/" local="129344772560000000" remote="129392519400000000" />
<file name="xls.png" server="atlassonoro.gaiared.com//httpdocs/" local="129344772560000000" remote="129392519400000000" />
</dwsync>