<?xml version="1.0" encoding="utf-8" ?>
<dwsync>
<file name="bg-leftcol.jpg" server="C:/xampp/htdocs/AtlasSonoroBocetoPreliminar/" local="129388952807102589" remote="129388952800000000" />
<file name="bg-main.jpg" server="C:/xampp/htdocs/AtlasSonoroBocetoPreliminar/" local="129388949506533807" remote="129388949500000000" />
<file name="figure-leftcol.png" server="C:/xampp/htdocs/AtlasSonoroBocetoPreliminar/" local="129388953739085895" remote="129388953730000000" />
<file name="head-tipo.png" server="C:/xampp/htdocs/AtlasSonoroBocetoPreliminar/" local="129389059829653928" remote="129389059820000000" />
<file name="home-woman.png" server="C:/xampp/htdocs/AtlasSonoroBocetoPreliminar/" local="129389736777154932" remote="129389736770000000" />
<file name="menu-rectangle.png" server="C:/xampp/htdocs/AtlasSonoroBocetoPreliminar/" local="129388945853704877" remote="129388945850000000" />
<file name="nav-amazonia.png" server="C:/xampp/htdocs/AtlasSonoroBocetoPreliminar/" local="129388957309530113" remote="129388957300000000" />
<file name="nav-costa.png" server="C:/xampp/htdocs/AtlasSonoroBocetoPreliminar/" local="129388957999579581" remote="129388957990000000" />
<file name="nav-patrimonio-sonoro.png" server="C:/xampp/htdocs/AtlasSonoroBocetoPreliminar/" local="129388955195529199" remote="129388955190000000" />
<file name="nav-sierra.png" server="C:/xampp/htdocs/AtlasSonoroBocetoPreliminar/" local="129388965441065210" remote="129388965440000000" />
<file name="nav-vivo.png" server="C:/xampp/htdocs/AtlasSonoroBocetoPreliminar/" local="129388956957349969" remote="129388956950000000" />
<file name="search-placeholder.png" server="C:/xampp/htdocs/AtlasSonoroBocetoPreliminar/" local="129388947981206563" remote="129388947980000000" />
<file name="bg-leftcol.jpg" server="atlassonoro.gaiared.com//httpdocs/" local="129388952807102589" remote="129392079600000000" />
<file name="bg-main.jpg" server="atlassonoro.gaiared.com//httpdocs/" local="129388949506533807" remote="129392079600000000" />
<file name="figure-leftcol.png" server="atlassonoro.gaiared.com//httpdocs/" local="129388953739085895" remote="129392080200000000" />
<file name="head-tipo.png" server="atlassonoro.gaiared.com//httpdocs/" local="129389059829653928" remote="129392080200000000" />
<file name="home-woman.png" server="atlassonoro.gaiared.com//httpdocs/" local="129389736777154932" remote="129392080200000000" />
<file name="menu-rectangle.png" server="atlassonoro.gaiared.com//httpdocs/" local="129388945853704877" remote="129392080200000000" />
<file name="nav-amazonia.png" server="atlassonoro.gaiared.com//httpdocs/" local="129388957309530113" remote="129392080200000000" />
<file name="nav-costa.png" server="atlassonoro.gaiared.com//httpdocs/" local="129388957999579581" remote="129392080200000000" />
<file name="nav-patrimonio-sonoro.png" server="atlassonoro.gaiared.com//httpdocs/" local="129388955195529199" remote="129392080200000000" />
<file name="nav-sierra.png" server="atlassonoro.gaiared.com//httpdocs/" local="129388965441065210" remote="129392080200000000" />
<file name="nav-vivo.png" server="atlassonoro.gaiared.com//httpdocs/" local="129388956957349969" remote="129392080200000000" />
<file name="search-placeholder.png" server="atlassonoro.gaiared.com//httpdocs/" local="129388947981206563" remote="129392080200000000" />
<file name="menu-rectangle-1a.png" server="C:/xampp/htdocs/AtlasSonoroBocetoPreliminar/" local="129389754688519403" remote="129389754680000000" />
<file name="menu-rectangle-1b.png" server="C:/xampp/htdocs/AtlasSonoroBocetoPreliminar/" local="129389754945764117" remote="129389754940000000" />
<file name="menu-rectangle-2a.png" server="C:/xampp/htdocs/AtlasSonoroBocetoPreliminar/" local="129389755271162729" remote="129389755270000000" />
<file name="menu-rectangle-2b.png" server="C:/xampp/htdocs/AtlasSonoroBocetoPreliminar/" local="129389755697037087" remote="129389755690000000" />
<file name="menu-rectangle-3a.png" server="C:/xampp/htdocs/AtlasSonoroBocetoPreliminar/" local="129389755967492557" remote="129389755960000000" />
<file name="menu-rectangle-3b.png" server="C:/xampp/htdocs/AtlasSonoroBocetoPreliminar/" local="129389756194715553" remote="129389756190000000" />
<file name="menu-rectangle-1a.png" server="atlassonoro.gaiared.com//httpdocs/" local="129389754688519403" remote="129392080200000000" />
<file name="menu-rectangle-1b.png" server="atlassonoro.gaiared.com//httpdocs/" local="129389754945764117" remote="129392080200000000" />
<file name="menu-rectangle-2a.png" server="atlassonoro.gaiared.com//httpdocs/" local="129389755271162729" remote="129392080200000000" />
<file name="menu-rectangle-2b.png" server="atlassonoro.gaiared.com//httpdocs/" local="129389755697037087" remote="129392080200000000" />
<file name="menu-rectangle-3a.png" server="atlassonoro.gaiared.com//httpdocs/" local="129389755967492557" remote="129392080200000000" />
<file name="menu-rectangle-3b.png" server="atlassonoro.gaiared.com//httpdocs/" local="129389756194715553" remote="129392080200000000" />
<file name="nav-arqueologico.png" server="atlassonoro.gaiared.com//httpdocs/" local="129388956066449013" remote="129392080200000000" />
<file name="nav-arqueologico.png" server="C:/xampp/htdocs/AtlasSonoroBocetoPreliminar/" local="129388956066449013" remote="129388956060000000" />
<file name="bg-amazonia.jpg" server="C:/xampp/htdocs/AtlasSonoroBocetoPreliminar/" local="129391697767202784" remote="129391697760000000" />
<file name="bg-costa.jpg" server="C:/xampp/htdocs/AtlasSonoroBocetoPreliminar/" local="129391810328610928" remote="129391810320000000" />
<file name="bg-sierra.jpg" server="C:/xampp/htdocs/AtlasSonoroBocetoPreliminar/" local="129391808077192155" remote="129391808070000000" />
<file name="head-tipo-amazonia.png" server="C:/xampp/htdocs/AtlasSonoroBocetoPreliminar/" local="129391679232202643" remote="129391679230000000" />
<file name="head-tipo-costa.png" server="C:/xampp/htdocs/AtlasSonoroBocetoPreliminar/" local="129391690741200920" remote="129391690740000000" />
<file name="head-tipo-sierra.png" server="C:/xampp/htdocs/AtlasSonoroBocetoPreliminar/" local="129391693805966214" remote="129391693800000000" />
<file name="siekopai.png" server="C:/xampp/htdocs/AtlasSonoroBocetoPreliminar/" local="129391723557567909" remote="129391723550000000" />
<file name="menu-rectangle-siekopai.png" server="C:/xampp/htdocs/AtlasSonoroBocetoPreliminar/" local="129391727805640884" remote="129391727800000000" />
<file name="button-detalles.png" server="C:/xampp/htdocs/AtlasSonoroBocetoPreliminar/" local="129391824451948737" remote="129391824450000000" />
<file name="button-galeria.png" server="C:/xampp/htdocs/AtlasSonoroBocetoPreliminar/" local="129391833298724744" remote="129391833290000000" />
<file name="button-instrumentos.png" server="C:/xampp/htdocs/AtlasSonoroBocetoPreliminar/" local="129391832771104566" remote="129391832770000000" />
<file name="button-musica.png" server="C:/xampp/htdocs/AtlasSonoroBocetoPreliminar/" local="129391832158889549" remote="129391832150000000" />
<file name="bg-amazonia.jpg" server="atlassonoro.gaiared.com//httpdocs/" local="129391697767202784" remote="129392079600000000" />
<file name="bg-costa.jpg" server="atlassonoro.gaiared.com//httpdocs/" local="129391810328610928" remote="129392079600000000" />
<file name="bg-sierra.jpg" server="atlassonoro.gaiared.com//httpdocs/" local="129391808077192155" remote="129392080200000000" />
<file name="button-detalles.png" server="atlassonoro.gaiared.com//httpdocs/" local="129391824451948737" remote="129392080200000000" />
<file name="button-galeria.png" server="atlassonoro.gaiared.com//httpdocs/" local="129391833298724744" remote="129392080200000000" />
<file name="button-instrumentos.png" server="atlassonoro.gaiared.com//httpdocs/" local="129391832771104566" remote="129392080200000000" />
<file name="button-musica.png" server="atlassonoro.gaiared.com//httpdocs/" local="129391832158889549" remote="129392080200000000" />
<file name="head-tipo-amazonia.png" server="atlassonoro.gaiared.com//httpdocs/" local="129391679232202643" remote="129392080200000000" />
<file name="head-tipo-costa.png" server="atlassonoro.gaiared.com//httpdocs/" local="129391690741200920" remote="129392080200000000" />
<file name="head-tipo-sierra.png" server="atlassonoro.gaiared.com//httpdocs/" local="129391693805966214" remote="129392080200000000" />
<file name="menu-rectangle-siekopai.png" server="atlassonoro.gaiared.com//httpdocs/" local="129391727805640884" remote="129392080200000000" />
<file name="siekopai.png" server="atlassonoro.gaiared.com//httpdocs/" local="129391723557567909" remote="129392080200000000" />
<file name="intro.jpg" server="C:/xampp/htdocs/AtlasSonoroBocetoPreliminar/" local="129392273574968919" remote="129392273570000000" />
<file name="intro_r1_c1.jpg" server="C:/xampp/htdocs/AtlasSonoroBocetoPreliminar/" local="129392274536483914" remote="129392274530000000" />
<file name="intro_r2_c1.jpg" server="C:/xampp/htdocs/AtlasSonoroBocetoPreliminar/" local="129392274536903938" remote="129392274530000000" />
<file name="intro_r2_c3.jpg" server="C:/xampp/htdocs/AtlasSonoroBocetoPreliminar/" local="129392274537373965" remote="129392274530000000" />
<file name="intro_r2_c7.jpg" server="C:/xampp/htdocs/AtlasSonoroBocetoPreliminar/" local="129392274537753987" remote="129392274530000000" />
<file name="intro_r3_c3.jpg" server="C:/xampp/htdocs/AtlasSonoroBocetoPreliminar/" local="129392274537863993" remote="129392274530000000" />
<file name="intro_r4_c1.jpg" server="C:/xampp/htdocs/AtlasSonoroBocetoPreliminar/" local="129392274539374080" remote="129392274530000000" />
<file name="intro_r4_c2.jpg" server="C:/xampp/htdocs/AtlasSonoroBocetoPreliminar/" local="129392274539604093" remote="129392274530000000" />
<file name="intro_r4_c4.jpg" server="C:/xampp/htdocs/AtlasSonoroBocetoPreliminar/" local="129392274540344135" remote="129392274540000000" />
<file name="intro_r4_c5.jpg" server="C:/xampp/htdocs/AtlasSonoroBocetoPreliminar/" local="129392274540554147" remote="129392274540000000" />
<file name="intro_r4_c8.jpg" server="C:/xampp/htdocs/AtlasSonoroBocetoPreliminar/" local="129392274541264188" remote="129392274540000000" />
<file name="intro_r5_c2.jpg" server="C:/xampp/htdocs/AtlasSonoroBocetoPreliminar/" local="129392274541784217" remote="129392274540000000" />
<file name="intro_r6_c10.jpg" server="C:/xampp/htdocs/AtlasSonoroBocetoPreliminar/" local="129392274542744272" remote="129392274540000000" />
<file name="intro_r6_c5.jpg" server="C:/xampp/htdocs/AtlasSonoroBocetoPreliminar/" local="129392274542154239" remote="129392274540000000" />
<file name="intro_r6_c9.jpg" server="C:/xampp/htdocs/AtlasSonoroBocetoPreliminar/" local="129392274542344249" remote="129392274540000000" />
<file name="intro_r7_c9.jpg" server="C:/xampp/htdocs/AtlasSonoroBocetoPreliminar/" local="129392274542914282" remote="129392274540000000" />
<file name="intro_r8_c11.jpg" server="C:/xampp/htdocs/AtlasSonoroBocetoPreliminar/" local="129392274543374308" remote="129392274540000000" />
<file name="intro_r8_c5.jpg" server="C:/xampp/htdocs/AtlasSonoroBocetoPreliminar/" local="129392274543014288" remote="129392274540000000" />
<file name="intro_r8_c6.jpg" server="C:/xampp/htdocs/AtlasSonoroBocetoPreliminar/" local="129392274543254302" remote="129392274540000000" />
<file name="intro_r9_c6.jpg" server="C:/xampp/htdocs/AtlasSonoroBocetoPreliminar/" local="129392274544154353" remote="129392274540000000" />
<file name="spacer.gif" server="C:/xampp/htdocs/AtlasSonoroBocetoPreliminar/" local="129392274536053890" remote="129392274530000000" />
<file name="video.png" server="C:/xampp/htdocs/AtlasSonoroBocetoPreliminar/" local="129392300746003013" remote="129392300740000000" />
</dwsync>